{
  "version": "5.10.1",
  "flags": {},
  "shapes": [
    {
      "label": "crater",
      "points": [
        [
          2341.3846153846152,
          653.7435897435898
        ],
        [
          2238.8205128205127,
          653.7435897435898
        ],
        [
          2123.4358974358975,
          679.3846153846155
        ],
        [
          2067.025641025641,
          702.4615384615385
        ],
        [
          2174.7179487179487,
          730.6666666666667
        ],
        [
          2297.7948717948716,
          740.9230769230769
        ],
        [
          2351.0,
          745.5496098104794
        ],
        [
          2351.0,
          656.3076923076924
        ]
      ],
      "group_id": null,
      "description": "",
      "shape_type": "polygon",
      "flags": {},
      "mask": null
    },
    {
      "label": "crater",
      "points": [
        [
          1446.5128205128208,
          530.6666666666667
        ],
        [
          1615.7435897435898,
          543.4871794871796
        ],
        [
          1743.9487179487178,
          515.2820512820514
        ],
        [
          1738.8205128205127,
          481.948717948718
        ],
        [
          1646.5128205128208,
          479.3846153846155
        ],
        [
          1523.4358974358975,
          479.3846153846155
        ],
        [
          1433.6923076923076,
          497.33333333333337
        ],
        [
          1408.0512820512822,
          520.4102564102565
        ]
      ],
      "group_id": null,
      "description": "",
      "shape_type": "polygon",
      "flags": {},
      "mask": null
    },
    {
      "label": "crater",
      "points": [
        [
          1261.897435897436,
          643.4871794871796
        ],
        [
          1423.4358974358975,
          661.4358974358975
        ],
        [
          1549.0769230769233,
          640.923076923077
        ],
        [
          1523.4358974358975,
          615.2820512820513
        ],
        [
          1392.6666666666665,
          607.5897435897436
        ],
        [
          1315.7435897435898,
          607.5897435897436
        ],
        [
          1220.871794871795,
          607.5897435897436
        ],
        [
          1182.4102564102564,
          622.974358974359
        ]
      ],
      "group_id": null,
      "description": "",
      "shape_type": "polygon",
      "flags": {},
      "mask": null
    },
    {
      "label": "crater",
      "points": [
        [
          1415.7435897435898,
          974.2564102564103
        ],
        [
          1556.769230769231,
          956.3076923076924
        ],
        [
          1656.769230769231,
          915.2820512820513
        ],
        [
          1618.3076923076924,
          892.2051282051283
        ],
        [
          1526.0,
          897.3333333333334
        ],
        [
          1408.0512820512822,
          933.2307692307693
        ],
        [
          1374.7179487179487,
          961.4358974358975
        ]
      ],
      "group_id": null,
      "description": "",
      "shape_type": "polygon",
      "flags": {},
      "mask": null
    },
    {
      "label": "crater",
      "points": [
        [
          777.2820512820514,
          1115.2820512820513
        ],
        [
          872.1538461538463,
          1110.1538461538462
        ],
        [
          933.6923076923077,
          1076.820512820513
        ],
        [
          859.3333333333334,
          1066.5641025641025
        ],
        [
          769.5897435897436,
          1066.5641025641025
        ],
        [
          759.3333333333334,
          1089.6410256410256
        ]
      ],
      "group_id": null,
      "description": "",
      "shape_type": "polygon",
      "flags": {},
      "mask": null
    },
    {
      "label": "crater",
      "points": [
        [
          1269.5897435897436,
          1115.2820512820513
        ],
        [
          1367.025641025641,
          1107.5897435897436
        ],
        [
          1400.3589743589746,
          1069.128205128205
        ],
        [
          1302.9230769230771,
          1071.6923076923076
        ]
      ],
      "group_id": null,
      "description": "",
      "shape_type": "polygon",
      "flags": {},
      "mask": null
    },
    {
      "label": "crater",
      "points": [
        [
          1451.6410256410259,
          1051.1794871794873
        ],
        [
          1487.5384615384614,
          1051.1794871794873
        ],
        [
          1520.871794871795,
          1043.4871794871794
        ],
        [
          1497.794871794872,
          1020.4102564102564
        ],
        [
          1436.2564102564102,
          1020.4102564102564
        ]
      ],
      "group_id": null,
      "description": "",
      "shape_type": "polygon",
      "flags": {},
      "mask": null
    },
    {
      "label": "crater",
      "points": [
        [
          1026.0,
          1597.3333333333333
        ],
        [
          1143.9487179487182,
          1597.3333333333333
        ],
        [
          1195.2307692307695,
          1569.128205128205
        ],
        [
          1126.0,
          1540.923076923077
        ],
        [
          1041.3846153846152,
          1558.871794871795
        ],
        [
          987.5384615384615,
          1574.2564102564102
        ]
      ],
      "group_id": null,
      "description": "",
      "shape_type": "polygon",
      "flags": {},
      "mask": null
    },
    {
      "label": "crater",
      "points": [
        [
          210.6153846153847,
          1648.6153846153845
        ],
        [
          418.3076923076924,
          1651.1794871794873
        ],
        [
          551.6410256410257,
          1625.5384615384614
        ],
        [
          608.0512820512821,
          1610.1538461538462
        ],
        [
          538.8205128205129,
          1576.820512820513
        ],
        [
          413.1794871794873,
          1579.3846153846155
        ],
        [
          256.7692307692309,
          1602.4615384615386
        ],
        [
          161.89743589743603,
          1622.974358974359
        ]
      ],
      "group_id": null,
      "description": "",
      "shape_type": "polygon",
      "flags": {},
      "mask": null
    },
    {
      "label": "crater",
      "points": [
        [
          141.38461538461547,
          515.2820512820514
        ],
        [
          318.3076923076924,
          505.0256410256411
        ],
        [
          533.6923076923077,
          505.0256410256411
        ],
        [
          513.1794871794873,
          476.82051282051293
        ],
        [
          395.2307692307693,
          464.0000000000001
        ],
        [
          254.2051282051283,
          464.0000000000001
        ],
        [
          123.43589743589752,
          469.1282051282052
        ],
        [
          113.1794871794873,
          505.0256410256411
        ]
      ],
      "group_id": null,
      "description": "",
      "shape_type": "polygon",
      "flags": {},
      "mask": null
    },
    {
      "label": "crater",
      "points": [
        [
          1431.128205128205,
          199.89743589743597
        ],
        [
          1508.0512820512822,
          205.0256410256411
        ],
        [
          1574.7179487179487,
          189.64102564102572
        ],
        [
          1538.8205128205127,
          179.38461538461547
        ],
        [
          1474.7179487179487,
          176.8205128205129
        ],
        [
          1408.0512820512822,
          174.25641025641033
        ]
      ],
      "group_id": null,
      "description": "",
      "shape_type": "polygon",
      "flags": {},
      "mask": null
    },
    {
      "label": "rock",
      "points": [
        [
          1202.9230769230771,
          799.8974358974359
        ],
        [
          1251.6410256410259,
          799.8974358974359
        ],
        [
          1251.6410256410259,
          748.6153846153846
        ],
        [
          1190.102564102564,
          761.4358974358975
        ]
      ],
      "group_id": null,
      "description": "",
      "shape_type": "polygon",
      "flags": {},
      "mask": null
    },
    {
      "label": "rock",
      "points": [
        [
          636.2564102564104,
          471.69230769230774
        ],
        [
          661.897435897436,
          471.69230769230774
        ],
        [
          654.2051282051283,
          425.53846153846166
        ],
        [
          626.0000000000001,
          433.2307692307693
        ]
      ],
      "group_id": null,
      "description": "",
      "shape_type": "polygon",
      "flags": {},
      "mask": null
    }
  ],
  "imagePath": "..\\images_part01\\CE4_GRAS_TCAM-I-008_SCI_N_20190106033414_20190106033414_0004_A.png",
  "imageData": null,
  "imageHeight": 1728,
  "imageWidth": 2352
}